sdif_mcp/__init__.py
sdif_mcp/prompt.py
sdif_mcp/server.py
sdif_mcp-0.2.5.dist-info/LICENSE
sdif_mcp-0.2.5.dist-info/METADATA
sdif_mcp-0.2.5.dist-info/WHEEL
sdif_mcp-0.2.5.dist-info/entry_points.txt
sdif_mcp-0.2.5.dist-info/RECORD
