Metadata-Version: 2.3
Name: sdif-mcp
Version: 0.2.5
Summary: SDIF MCP
License: MIT
Author: Syncpulse
Maintainer: Bryan Djafer
Maintainer-email: bryan.djafer@syncpulse.fr
Requires-Python: >=3.10,<4.0
Classifier: License :: OSI Approved :: MIT License
Classifier: Programming Language :: Python :: 3
Classifier: Programming Language :: Python :: 3.10
Classifier: Programming Language :: Python :: 3.11
Classifier: Programming Language :: Python :: 3.12
Classifier: Programming Language :: Python :: 3.13
Requires-Dist: fastmcp (>=2.3.0,<3.0.0)
Requires-Dist: sdif-db (>=0.1.0)
